pytest_httpserver/__init__.py
pytest_httpserver/blocking_httpserver.py
pytest_httpserver/hooks.py
pytest_httpserver/httpserver.py
pytest_httpserver/py.typed
pytest_httpserver/pytest_plugin.py
pytest_httpserver-1.1.1.dist-info/LICENSE
pytest_httpserver-1.1.1.dist-info/METADATA
pytest_httpserver-1.1.1.dist-info/WHEEL
pytest_httpserver-1.1.1.dist-info/entry_points.txt
pytest_httpserver-1.1.1.dist-info/RECORD
