Metadata-Version: 2.1
Name: pytest_httpserver
Version: 1.1.1
Summary: pytest-httpserver is a httpserver for pytest
Home-page: https://github.com/csernazs/pytest-httpserver
License: MIT
Author: Zsolt Cserna
Author-email: cserna.zsolt@gmail.com
Requires-Python: >=3.8
Classifier: Development Status :: 3 - Alpha
Classifier: Framework :: Pytest
Classifier: Intended Audience :: Developers
Classifier: License :: OSI Approved :: MIT License
Classifier: Operating System :: OS Independent
Classifier: Programming Language :: Python :: 3
Classifier: Programming Language :: Python :: 3.8
Classifier: Programming Language :: Python :: 3.9
Classifier: Programming Language :: Python :: 3.10
Classifier: Programming Language :: Python :: 3.11
Classifier: Programming Language :: Python :: 3.12
Classifier: Programming Language :: Python :: 3.13
Classifier: Topic :: Software Development :: Libraries :: Python Modules
Requires-Dist: Werkzeug (>=2.0.0)
Project-URL: Bug Tracker, https://github.com/csernazs/pytest-httpserver/issues
Project-URL: Documentation, https://pytest-httpserver.readthedocs.io/en/latest/
Project-URL: Repository, https://github.com/csernazs/pytest-httpserver
